boosty_api/__init__.py
boosty_api/boosty_api.py
pyboostyapi-1.0.6.dist-info/licenses/LICENSE
pyboostyapi-1.0.6.dist-info/METADATA
pyboostyapi-1.0.6.dist-info/WHEEL
pyboostyapi-1.0.6.dist-info/top_level.txt
pyboostyapi-1.0.6.dist-info/RECORD
