Metadata-Version: 2.4
Name: PyBoostyApi
Version: 1.0.6
Summary: PyBoostyAPI is a powerful asynchronous Python library for seamless interaction with the Boosty.to API
Home-page: https://github.com/HOCKI1/py_boosty_api
Author: HOCKI1
Author-email: hocki1.official@yandex.ru
Project-URL: Source, https://github.com/HOCKI1/py_boosty_api
Project-URL: Tracker, https://github.com/HOCKI1/py_boosty_api/issues
Keywords: boosty api async aiohttp donations subscribers
Classifier: Programming Language :: Python :: 3
Classifier: License :: OSI Approved :: MIT License
Classifier: Operating System :: OS Independent
Requires-Python: >=3.7
License-File: LICENSE
Requires-Dist: aiohttp
Requires-Dist: requests
Requires-Dist: beautifulsoup4
Dynamic: author
Dynamic: author-email
Dynamic: classifier
Dynamic: description
Dynamic: description-content-type
Dynamic: home-page
Dynamic: keywords
Dynamic: license-file
Dynamic: project-url
Dynamic: requires-dist
Dynamic: requires-python
Dynamic: summary
